pyforceatlas2/__init__.py
pyforceatlas2/layout.py
pyforceatlas2/pyforceatlas2.py
pyforceatlas2-0.0.5.dist-info/licenses/LICENSE
pyforceatlas2-0.0.5.dist-info/METADATA
pyforceatlas2-0.0.5.dist-info/WHEEL
pyforceatlas2-0.0.5.dist-info/top_level.txt
pyforceatlas2-0.0.5.dist-info/RECORD
