Metadata-Version: 2.4
Name: pyforceatlas2
Version: 0.0.5
Summary: Fast Gephi's ForceAtlas2 graph layout algorithm written in Python for Python.
Author-email: Ira Horecka <ira89@icloud.com>
License: GPL-3.0-or-later
Project-URL: Homepage, https://github.com/irahorecka/pyforceatlas2
Classifier: Development Status :: 4 - Beta
Classifier: Intended Audience :: Developers
Classifier: Intended Audience :: Science/Research
Classifier: Operating System :: OS Independent
Classifier: Programming Language :: Python :: 3
Classifier: Programming Language :: Python :: 3.9
Classifier: Topic :: Scientific/Engineering :: Visualization
Classifier: Topic :: Scientific/Engineering :: Information Analysis
Classifier: Topic :: Software Development :: Libraries :: Python Modules
Requires-Python: >=3.8
License-File: LICENSE
Requires-Dist: networkx
Requires-Dist: numpy
Requires-Dist: python-igraph
Requires-Dist: scipy
Requires-Dist: tqdm
Dynamic: license-file
